JIT/__config__.py
JIT/__future__.py
JIT/__init__.py
JIT/_classes.py
JIT/_jit_internal.py
JIT/_namedtensor_internals.py
JIT/_ops.py
JIT/_overrides.py
JIT/_six.py
JIT/_storage_docs.py
JIT/_tensor_docs.py
JIT/_tensor_str.py
JIT/_torch_docs.py
JIT/_utils.py
JIT/_utils_internal.py
JIT/client.py
JIT/functional.py
JIT/hub.py
JIT/quasirandom.py
JIT/random.py
JIT/serialization.py
JIT/server.py
JIT/storage.py
JIT/tensor.py
JIT/version.py
JIT/tools/__init__.py
JIT/tools/__short_time.py
JIT-0.2.6.dist-info/METADATA
JIT-0.2.6.dist-info/WHEEL
JIT-0.2.6.dist-info/top_level.txt
JIT-0.2.6.dist-info/RECORD
