Metadata-Version: 2.1
Name: JIT
Version: 0.2.6
Summary: This is a package for my just in time
Home-page: https://github.com/NocoldBob/JIT
Author: fastbiubiu
Author-email: fastbiubiu@163.com
License: UNKNOWN
Platform: UNKNOWN
Classifier: Programming Language :: Python :: 3
Classifier: License :: OSI Approved :: MIT License
Classifier: Operating System :: OS Independent
